xaal/__init__.py
xaal/netatmo/__init__.py
xaal/netatmo/__main__.py
xaal/netatmo/gw.py
xaal/netatmo/netatmo.py
xaal/netatmo/token_manager.py
xaal_netatmo-0.3.1.dist-info/METADATA
xaal_netatmo-0.3.1.dist-info/WHEEL
xaal_netatmo-0.3.1.dist-info/top_level.txt
xaal_netatmo-0.3.1.dist-info/RECORD
