Metadata-Version: 2.4
Name: xaal.netatmo
Version: 0.3.1
Summary: Netatmo Weather Station
Author-email: Caifeng BAO <caifeng.bao@imt-atlantique.fr>, Jerome Kerdreux <Jerome.Kerdreux@imt-atlantique.fr>
License-Expression: GPL-3.0-or-later
Project-URL: Homepage, https://recherche.imt-atlantique.fr/xaal/
Project-URL: Documentation, https://gitlab.imt-atlantique.fr/xaal/code/python/-/blob/main/devices/protocols/Netatmo/README.rst
Project-URL: Source, https://gitlab.imt-atlantique.fr/xaal/code/python/-/tree/main/devices/protocols/Netatmo
Keywords: xaal,netatmo,weather,station
Classifier: Programming Language :: Python
Classifier: Topic :: Home Automation
Requires-Dist: xaal.lib
Requires-Dist: requests
